BiliUtil/__init__.py
BiliUtil/__version__.py
BiliUtil/Space/__init__.py
BiliUtil/Space/channel.py
BiliUtil/Space/user.py
BiliUtil/Util/__init__.py
BiliUtil/Util/tools.py
BiliUtil/Video/__init__.py
BiliUtil/Video/album.py
BiliUtil/Video/fetcher.py
BiliUtil/Video/filter.py
BiliUtil/Video/task.py
BiliUtil/Video/video.py
BiliUtil-0.2.3.dist-info/METADATA
BiliUtil-0.2.3.dist-info/WHEEL
BiliUtil-0.2.3.dist-info/top_level.txt
BiliUtil-0.2.3.dist-info/RECORD
