Metadata-Version: 2.1
Name: BiliUtil
Version: 0.2.3
Summary: Bilibili.com（B站）视频下载工具
Home-page: https://github.com/wolfbolin/BiliUtil
Author: WolfBolin
Author-email: mailto@wolfbolin.com
License: MIT
Platform: UNKNOWN
Classifier: License :: OSI Approved :: MIT License
Classifier: Programming Language :: Python
Classifier: Programming Language :: Python :: 3
Classifier: Programming Language :: Python :: 3.6
Classifier: Programming Language :: Python :: Implementation :: CPython
Classifier: Programming Language :: Python :: Implementation :: PyPy
Requires-Python: >=3.6.0
Requires-Dist: requests
Requires-Dist: fake-useragent
